ancypatch
