Metadata-Version: 1.0
Name: ancypatch
Version: 0.1.3
Summary: helper scripts to patch a binary, forked version of patchkit
Home-page: http://anciety.cn/ancypatch/index.html
Author: Anciety
Author-email: ding641880047@126.com
License: UNKNOWN
Keywords: patch binary
Platform: UNKNOWN
